[
  {
    "pk": 1,
    "fields": {
      "name": "Abdominal"
    }
  },
  {
    "pk": 2,
    "fields": {
      "name": "Bicep"
    }
  },
  {
    "pk": 3,
    "fields": {
      "name": "Calf"
    }
  },
  {
    "pk": 4,
    "fields": {
      "name": "Chest"
    }
  },
  {
    "pk": 5,
    "fields": {
      "name": "Forearm - Inner"
    }
  },
  {
    "pk": 6,
    "fields": {
      "name": "Forearm - Outer"
    }
  },
  {
    "pk": 7,
    "fields": {
      "name": "Glute"
    }
  },
  {
    "pk": 8,
    "fields": {
      "name": "Hamstring"
    }
  },
  {
    "pk": 9,
    "fields": {
      "name": "Lat"
    }
  },
  {
    "pk": 10,
    "fields": {
      "name": "Lower Back"
    }
  },
  {
    "pk": 11,
    "fields": {
      "name": "Oblique"
    }
  },
  {
    "pk": 12,
    "fields": {
      "name": "Quad"
    }
  },
  {
    "pk": 13,
    "fields": {
      "name": "Rotator Cuff - Back"
    }
  },
  {
    "pk": 14,
    "fields": {
      "name": "Rotator Cuff - Front"
    }
  },
  {
    "pk": 15,
    "fields": {
      "name": "Shoulder - Back"
    }
  },
  {
    "pk": 16,
    "fields": {
      "name": "Shoulder - Front"
    }
  },
  {
    "pk": 17,
    "fields": {
      "name": "Shoulder - Side"
    }
  },
  {
    "pk": 18,
    "fields": {
      "name": "Thigh - Inner"
    }
  },
  {
    "pk": 19,
    "fields": {
      "name": "Thigh - Outer"
    }
  },
  {
    "pk": 20,
    "fields": {
      "name": "Trap"
    }
  },
  {
    "pk": 21,
    "fields": {
      "name": "Tricep"
    }
  }
]
